cgrad/__init__.py
cgrad/autograd/calcgrad.cpython-312-darwin.so
cgrad/randoms/__init__.py
cgrad/randoms/random_methods.cpython-312-darwin.so
cgrad/randoms/random_methods.pyi
cgrad/tensor/Tensorwrapper.cpython-312-darwin.so
cgrad/tensor/Tensorwrapper.pyi
cgrad/tensor/__init__.py
CGrad-0.1.1.dist-info/LICENSE
CGrad-0.1.1.dist-info/METADATA
CGrad-0.1.1.dist-info/WHEEL
CGrad-0.1.1.dist-info/top_level.txt
CGrad-0.1.1.dist-info/RECORD
