Metadata-Version: 2.1
Name: CGrad
Version: 0.1.1
Summary: A Cython-based tensor and autograd library
Home-page: https://github.com/Ruhaan838/CGrad
Author: Ruhaan
Author-email: ruhaan123dalal@gmail.com
License: MIT
License-File: LICENSE
Requires-Dist: numpy
